_ppmd.abi3.so
ppmd/__init__.py
ppmd/__init__.pyi
ppmd/__main__.py
ppmd/__main__.pyi
ppmd_cffi-0.5.0.dist-info/LICENSE
ppmd_cffi-0.5.0.dist-info/METADATA
ppmd_cffi-0.5.0.dist-info/WHEEL
ppmd_cffi-0.5.0.dist-info/entry_points.txt
ppmd_cffi-0.5.0.dist-info/top_level.txt
ppmd_cffi-0.5.0.dist-info/RECORD
