Metadata-Version: 2.1
Name: ppmd-cffi
Version: 0.5.0
Summary: PPMd compression/decompression library
Home-page: http://github.com/miurahr/ppmd
Author: Hiroshi Miura
Author-email: miurahr@linux.com
License: LGPL-2.1+
Keywords: ppmd,7-zip,compression
Platform: UNKNOWN
Classifier: Development Status :: 4 - Beta
Classifier: License :: OSI Approved :: GNU Lesser General Public License v2 or later (LGPLv2+)
Classifier: Operating System :: MacOS :: MacOS X
Classifier: Operating System :: Microsoft :: Windows
Classifier: Operating System :: POSIX
Classifier: Operating System :: POSIX :: Linux
Classifier: Programming Language :: Python
Classifier: Programming Language :: Python :: 3
Classifier: Programming Language :: Python :: 3.6
Classifier: Programming Language :: Python :: 3.7
Classifier: Programming Language :: Python :: 3.8
Classifier: Programming Language :: Python :: 3.9
Classifier: Programming Language :: Python :: 3 :: Only
Classifier: Topic :: Software Development :: Libraries :: Python Modules
Provides-Extra: test
Provides-Extra: check
Provides-Extra: docs
Provides-Extra: fuzzer
